Metadata-Version: 2.1
Name: ftdz_from_fyh1
Version: 1.0.5
Summary: a game.
Home-page: https://www.github.com/
Author: bob
Author-email: 56141537@qq.com
Classifier: Programming Language :: Python :: 3
Classifier: License :: OSI Approved :: MIT License
Classifier: Operating System :: OS Independent
Requires-Dist: pygame
Requires-Dist: requests
